{
  "parentCategories": [
    {
      "id": "1",
      "name": "Shopping"
    },
    {
      "id": "2",
      "name": "Bills and Utilities"
    },
    {
      "id": "4",
      "name": "Education"
    },
    {
      "id": "5",
      "name": "Entertaiment"
    }
  ],
  "categories": [
    {
      "id": "1",
      "name": "Internet",
      "parentCategory": "2"
    },
    {
      "id": "2",
      "name": "Mobile Phone",
      "parentCategory": "2"
    },
    {
      "id": "3",
      "name": "Rent",
      "parentCategory": "2"
    },
    {
      "id": "4",
      "name": "Alcohol",
      "parentCategory": "1"
    },
    {
      "id": "5",
      "name": "Grocery",
      "parentCategory": "1"
    },
    {
      "id": "6",
      "name": "Chemistry",
      "parentCategory": "1"
    },
    {
      "id": "7",
      "name": "Udemy Course",
      "parentCategory": "4"
    },
    {
      "id": "8",
      "name": "Restaurants and pubs",
      "parentCategory": "5"
    }
  ],
  "budgetCategories": [
    {
      "id": "1",
      "budget": 120.47,
      "categoryId": "1",
      "budgetId": "1"
    },
    {
      "id": "2",
      "budget": 39.99,
      "categoryId": "2",
      "budgetId": "1"
    },
    {
      "id": "3",
      "budget": 723,
      "categoryId": "3",
      "budgetId": "1"
    },
    {
      "id": "4",
      "budget": 30,
      "categoryId": "4",
      "budgetId": "1"
    },
    {
      "id": "5",
      "budget": 450,
      "categoryId": "5",
      "budgetId": "1"
    },
    {
      "id": "6",
      "budget": 80,
      "categoryId": "6",
      "budgetId": "1"
    }
  ],
  "budgets": [
    {
      "id": "1",
      "name": "April",
      "totalAmount": 2400
    }
  ],
  "transactions": [
    {
      "id": "1",
      "description": "Internet provider",
      "amount": 120.47,
      "categoryId": "1",
      "date": "2019-12-15T20:39:41.768Z",
      "budgetId": "1"
    },
    {
      "id": "2",
      "description": "Mobile network provider",
      "amount": 39.99,
      "categoryId": "2",
      "date": "2019-12-10T13:33:21.768Z",
      "budgetId": "1"
    },
    {
      "id": "3",
      "description": "Weekly shopping",
      "amount": 23.88,
      "categoryId": "6",
      "date": "2019-12-17T15:41:01.768Z",
      "budgetId": "1"
    },
    {
      "id": "4",
      "description": "Weekly Shopping #2",
      "amount": 12.48,
      "categoryId": "6",
      "date": "2019-12-17T12:41:01.768Z",
      "budgetId": "1"
    },
    {
      "id": "5",
      "description": "Dinner in restaurant",
      "amount": 35.68,
      "categoryId": "null",
      "date": "2019-12-18T13:38:41.768Z",
      "budgetId": "1"
    },
    {
      "description": "Default Agile Workflow",
      "amount": 123,
      "categoryId": "2",
      "date": "2020-02-13",
      "budgetId": "1",
      "id": "p1tYW2Q"
    }
  ]
}
